sorcererdb/__init__.py
sorcererdb/config.py
sorcererdb/core.py
sorcererdb/logging.py
sorcererdb/spell.py
sorcererdb-0.1.0a2.dist-info/licenses/LICENSE
sorcererdb-0.1.0a2.dist-info/METADATA
sorcererdb-0.1.0a2.dist-info/WHEEL
sorcererdb-0.1.0a2.dist-info/top_level.txt
sorcererdb-0.1.0a2.dist-info/RECORD
