Metadata-Version: 2.4
Name: sorcererdb
Version: 0.1.0a2
Summary: A magical Python database abstraction layer inspired by Sorcery
Author-email: Eric Harris <ericktheredd5875@gmail.com>
License-Expression: MIT
Requires-Python: >=3.10
License-File: LICENSE
Requires-Dist: mysql-connector-python>=8.0
Requires-Dist: loguru>=0.7.0
Provides-Extra: dev
Requires-Dist: pytest; extra == "dev"
Requires-Dist: pytest-cov; extra == "dev"
Requires-Dist: black; extra == "dev"
Requires-Dist: mypy; extra == "dev"
Dynamic: license-file
